reflex_azure_auth/__init__.py
reflex_azure_auth/config.py
reflex_azure_auth/endpoints.py
reflex_azure_auth/funcs.py
reflex_azure_auth/messageListener.js
reflex_azure_auth/message_listener.py
reflex_azure_auth/oidc.py
reflex_azure_auth/state.py
reflex_azure_auth/types.py
reflex_azure_auth/ui.py
reflex_azure_auth-0.1.1.dist-info/METADATA
reflex_azure_auth-0.1.1.dist-info/WHEEL
reflex_azure_auth-0.1.1.dist-info/RECORD
