Metadata-Version: 2.4
Name: reflex-azure-auth
Version: 0.1.1
Summary: Integration with Azure (Microsoft identity platform) OpenID Connect
Project-URL: homepage, https://reflex.dev/
Project-URL: documentation, https://enterprise.reflex.dev
Author-email: Masen Furer <masen@reflex.dev>
License-Expression: LicenseRef-Proprietary
Keywords: python,reflex,reflex-enterprise
Requires-Python: <4.0,>=3.10
Requires-Dist: authlib
Requires-Dist: httpx
Requires-Dist: reflex-enterprise>=0.3.0
Requires-Dist: reflex>=0.8.4
